fables/__init__.py
fables/api.py
fables/constants.py
fables/errors.py
fables/parse.py
fables/results.py
fables/table.py
fables/tree.py
fables-1.2.5.dist-info/LICENSE
fables-1.2.5.dist-info/METADATA
fables-1.2.5.dist-info/WHEEL
fables-1.2.5.dist-info/top_level.txt
fables-1.2.5.dist-info/zip-safe
fables-1.2.5.dist-info/RECORD
