Metadata-Version: 2.1
Name: fables
Version: 1.2.5
Summary: (F)ile T(ables)
Home-page: https://github.com/payscale/fables
Author: PayScale, Inc.
Author-email: pypi@payscale.com
License: Apache 2.0
Platform: UNKNOWN
Classifier: License :: OSI Approved :: Apache Software License
Classifier: Programming Language :: Python :: 3.7
Classifier: Topic :: Scientific/Engineering
Requires-Dist: pandas (==1.0.1)
Requires-Dist: cchardet (==2.1.7)
Requires-Dist: chardet (==3.0.4)
Requires-Dist: clevercsv (==0.7.0)
Requires-Dist: python-magic (==0.4.15)
Requires-Dist: xlrd (==1.2.0)
Requires-Dist: msoffcrypto-tool (==4.6.4)
Requires-Dist: pyxlsb (==1.0.6)
Requires-Dist: python-magic-bin (==0.4.14) ; platform_system == "Windows"
